makemessages_plus
