Metadata-Version: 1.0
Name: django-makemessages-plus
Version: 0.2
Summary: An django extension to support making messages from coffeescript files
Home-page: http://github.com/hoozecn/django-makemessages-plus
Author: Zhimin Wu
Author-email: hoozecn+dcmm@gmail.com
License: BSD License
Platform: UNKNOWN
Classifier: Framework :: Django
Classifier: Intended Audience :: Developers
Classifier: License :: OSI Approved :: BSD License
Classifier: Programming Language :: Python
Classifier: Programming Language :: Python :: 2.7
Classifier: Topic :: Internet :: WWW/HTTP
Classifier: Topic :: Internet :: WWW/HTTP :: Dynamic Content
